bsedata/__init__.py
bsedata/bse.py
bsedata/exceptions.py
bsedata/gainers.py
bsedata/indices.py
bsedata/losers.py
bsedata/quote.py
bsedata-0.5.4.dist-info/LICENSE
bsedata-0.5.4.dist-info/METADATA
bsedata-0.5.4.dist-info/WHEEL
bsedata-0.5.4.dist-info/top_level.txt
bsedata-0.5.4.dist-info/RECORD
